<Root><vspdData V="V20030529" Split="0"><DATA TYPE_CD="S" FIELD_CD="A.ITEM_CD" FIELD_NM="품목" FIELD_LEN="10" FIELD_TYPE="ED" DEFAULT_T="4" NEXT_SEQ="2" KEY_TAG="1" HIDDEN="F" SORT_DIR="ASC" SEQ="1" POS="4"/><DATA TYPE_CD="S" FIELD_CD="B.ITEM_NM" FIELD_NM="품목명" FIELD_LEN="20" FIELD_TYPE="ED" DEFAULT_T="5" NEXT_SEQ="1" KEY_TAG="2" HIDDEN="F" SORT_DIR="ASC" SEQ="2" POS="5"/><DATA TYPE_CD="S" FIELD_CD="B.SPEC" FIELD_NM="품목규격" FIELD_LEN="20" FIELD_TYPE="ED" DEFAULT_T="6" NEXT_SEQ="0" KEY_TAG="3" HIDDEN="F" SORT_DIR="ASC" SEQ="3" POS="6"/><DATA TYPE_CD="S" FIELD_CD="A.QTY" FIELD_NM="통관수량" FIELD_LEN="10" FIELD_TYPE="F3" DEFAULT_T="7" NEXT_SEQ="0" KEY_TAG="4" HIDDEN="F" SORT_DIR="ASC" SEQ="4" POS="7"/><DATA TYPE_CD="S" FIELD_CD="A.RECEIPT_QTY" FIELD_NM="입고수량" FIELD_LEN="10" FIELD_TYPE="F3" DEFAULT_T="8" NEXT_SEQ="0" KEY_TAG="5" HIDDEN="F" SORT_DIR="ASC" SEQ="5" POS="8"/><DATA TYPE_CD="S" FIELD_CD="A.UNIT" FIELD_NM="단위" FIELD_LEN="5" FIELD_TYPE="ED" DEFAULT_T="9" NEXT_SEQ="0" KEY_TAG="6" HIDDEN="F" SORT_DIR="ASC" SEQ="6" POS="9"/><DATA TYPE_CD="S" FIELD_CD="A.PRICE" FIELD_NM="단가" FIELD_LEN="10" FIELD_TYPE="FC" DEFAULT_T="10" NEXT_SEQ="0" KEY_TAG="7" HIDDEN="F" SORT_DIR="ASC" SEQ="7" POS="10"/><DATA TYPE_CD="S" FIELD_CD="A.DOC_AMT" FIELD_NM="통관금액" FIELD_LEN="15" FIELD_TYPE="FA" DEFAULT_T="11" NEXT_SEQ="0" KEY_TAG="8" HIDDEN="F" SORT_DIR="ASC" SEQ="8" POS="11"/><DATA TYPE_CD="S" FIELD_CD="C.CURRENCY" FIELD_NM="화폐" FIELD_LEN="5" FIELD_TYPE="ED" DEFAULT_T="12" NEXT_SEQ="0" KEY_TAG="9" HIDDEN="F" SORT_DIR="ASC" SEQ="9" POS="12"/><DATA TYPE_CD="S" FIELD_CD="XCH_RATE" FIELD_NM="환율" FIELD_LEN="10" FIELD_TYPE="FD" DEFAULT_T="13" NEXT_SEQ="0" KEY_TAG="10" HIDDEN="F" SORT_DIR="ASC" SEQ="10" POS="13"/><DATA TYPE_CD="S" FIELD_CD="A.LOC_AMT" FIELD_NM="통관자국금액" FIELD_LEN="10" FIELD_TYPE="FA" DEFAULT_T="14" NEXT_SEQ="0" KEY_TAG="11" HIDDEN="F" SORT_DIR="ASC" SEQ="11" POS="14"/><DATA TYPE_CD="S" FIELD_CD="A.CC_NO" FIELD_NM="통관관리번호" FIELD_LEN="13" FIELD_TYPE="ED" DEFAULT_T="15" NEXT_SEQ="0" KEY_TAG="12" HIDDEN="F" SORT_DIR="ASC" SEQ="12" POS="15"/><DATA TYPE_CD="S" FIELD_CD="A.CC_SEQ" FIELD_NM="통관순번" FIELD_LEN="10" FIELD_TYPE="ED" DEFAULT_T="16" NEXT_SEQ="0" KEY_TAG="13" HIDDEN="F" SORT_DIR="ASC" SEQ="13" POS="16"/><DATA TYPE_CD="S" FIELD_CD="D.BP_NM" FIELD_NM="수출자" FIELD_LEN="15" FIELD_TYPE="ED" DEFAULT_T="1" NEXT_SEQ="0" KEY_TAG="14" HIDDEN="F" SORT_DIR="ASC" SEQ="14" POS="1"/><DATA TYPE_CD="S" FIELD_CD="A. BL_NO" FIELD_NM="B/L번호" FIELD_LEN="13" FIELD_TYPE="ED" DEFAULT_T="2" NEXT_SEQ="0" KEY_TAG="15" HIDDEN="F" SORT_DIR="ASC" SEQ="15" POS="2"/><DATA TYPE_CD="S" FIELD_CD="A.BL_SEQ" FIELD_NM="B/L순번" FIELD_LEN="10" FIELD_TYPE="ED" DEFAULT_T="20" NEXT_SEQ="0" KEY_TAG="16" HIDDEN="F" SORT_DIR="ASC" SEQ="16" POS="20"/><DATA TYPE_CD="S" FIELD_CD="A.PO_NO" FIELD_NM="발주번호" FIELD_LEN="15" FIELD_TYPE="ED" DEFAULT_T="3" NEXT_SEQ="0" KEY_TAG="17" HIDDEN="F" SORT_DIR="ASC" SEQ="17" POS="3"/><DATA TYPE_CD="S" FIELD_CD="A.PO_SEQ" FIELD_NM="발주순번" FIELD_LEN="10" FIELD_TYPE="ED" DEFAULT_T="21" NEXT_SEQ="0" KEY_TAG="18" HIDDEN="F" SORT_DIR="ASC" SEQ="18" POS="21"/><DATA TYPE_CD="S" FIELD_CD="A.LC_NO" FIELD_NM="L/C번호" FIELD_LEN="20" FIELD_TYPE="ED" DEFAULT_T="22" NEXT_SEQ="0" KEY_TAG="19" HIDDEN="F" SORT_DIR="ASC" SEQ="19" POS="22"/><DATA TYPE_CD="S" FIELD_CD="A.LC_SEQ" FIELD_NM="L/C순번" FIELD_LEN="10" FIELD_TYPE="ED" DEFAULT_T="23" NEXT_SEQ="0" KEY_TAG="20" HIDDEN="F" SORT_DIR="ASC" SEQ="20" POS="23"/><DATA TYPE_CD="S" FIELD_CD="A.HS_CD" FIELD_NM="HS부호" FIELD_LEN="20" FIELD_TYPE="ED" DEFAULT_T="24" NEXT_SEQ="0" KEY_TAG="21" HIDDEN="F" SORT_DIR="ASC" SEQ="21" POS="24"/><DATA TYPE_CD="S" FIELD_CD="A.NET_WEIGHT" FIELD_NM="순중량" FIELD_LEN="15" FIELD_TYPE="F3" DEFAULT_T="25" NEXT_SEQ="0" KEY_TAG="22" HIDDEN="F" SORT_DIR="ASC" SEQ="22" POS="25"/><DATA TYPE_CD="S" FIELD_CD="F.QTY" FIELD_NM="B/L수량" FIELD_LEN="15" FIELD_TYPE="F3" DEFAULT_T="26" NEXT_SEQ="0" KEY_TAG="23" HIDDEN="F" SORT_DIR="ASC" SEQ="23" POS="26"/><DATA TYPE_CD="S" FIELD_CD="C.INCOTERMS" FIELD_NM="가격조건" FIELD_LEN="10" FIELD_TYPE="ED" DEFAULT_T="27" NEXT_SEQ="0" KEY_TAG="24" HIDDEN="F" SORT_DIR="ASC" SEQ="24" POS="27"/><DATA TYPE_CD="S" FIELD_CD="C.ID_DT" FIELD_NM="신고일" FIELD_LEN="15" FIELD_TYPE="DD" DEFAULT_T="17" NEXT_SEQ="0" KEY_TAG="25" HIDDEN="F" SORT_DIR="ASC" SEQ="25" POS="17"/><DATA TYPE_CD="S" FIELD_CD="C.IP_DT" FIELD_NM="면허일" FIELD_LEN="15" FIELD_TYPE="DD" DEFAULT_T="18" NEXT_SEQ="0" KEY_TAG="26" HIDDEN="F" SORT_DIR="ASC" SEQ="26" POS="18"/><DATA TYPE_CD="S" FIELD_CD="E.PUR_GRP_NM" FIELD_NM="구매그룹" FIELD_LEN="20" FIELD_TYPE="ED" DEFAULT_T="19" NEXT_SEQ="0" KEY_TAG="27" HIDDEN="F" SORT_DIR="ASC" SEQ="27" POS="19"/></vspdData></Root>
