<Root><vspdData V="V20081006" Split="2"><DATA POS="1" SEQ="1" FLAG="D"><CASE FLAG="D" HEADER="품목" COLWIDTH="9.75" HIDDEN="F"/></DATA><DATA POS="2" SEQ="2" FLAG="D"><CASE FLAG="D" HEADER="품목명" COLWIDTH="19.75" HIDDEN="F"/></DATA><DATA POS="3" SEQ="3" FLAG="D"><CASE FLAG="D" HEADER="규격" COLWIDTH="4.5" HIDDEN="F"/></DATA><DATA POS="4" SEQ="4" FLAG="D"><CASE FLAG="D" HEADER="Tracking No." COLWIDTH="4.625" HIDDEN="F"/></DATA><DATA POS="5" SEQ="5" FLAG="D"><CASE FLAG="D" HEADER="단위" COLWIDTH="6" HIDDEN="F"/></DATA><DATA POS="6" SEQ="6" FLAG="D"><CASE FLAG="D" HEADER="기초수량" COLWIDTH="15" HIDDEN="F"/></DATA><DATA POS="7" SEQ="7" FLAG="D"><CASE FLAG="D" HEADER="기초금액" COLWIDTH="15" HIDDEN="F"/></DATA><DATA POS="8" SEQ="8" FLAG="D"><CASE FLAG="D" HEADER="입고수량" COLWIDTH="15" HIDDEN="F"/></DATA><DATA POS="9" SEQ="9" FLAG="D"><CASE FLAG="D" HEADER="입고금액" COLWIDTH="15" HIDDEN="F"/></DATA><DATA POS="10" SEQ="10" FLAG="D"><CASE FLAG="D" HEADER="출고수량" COLWIDTH="15" HIDDEN="F"/></DATA><DATA POS="11" SEQ="11" FLAG="D"><CASE FLAG="D" HEADER="출고금액" COLWIDTH="15" HIDDEN="F"/></DATA><DATA POS="12" SEQ="12" FLAG="D"><CASE FLAG="D" HEADER="재고수량" COLWIDTH="15" HIDDEN="F"/></DATA><DATA POS="13" SEQ="13" FLAG="D"><CASE FLAG="D" HEADER="재고금액" COLWIDTH="15" HIDDEN="F"/></DATA></vspdData></Root>
