<Root><vspdData V="V20030220" Split="0"><DATA TYPE_CD="S" FIELD_CD="GL_NO" FIELD_NM="전표번호" FIELD_LEN="15" FIELD_TYPE="ED" DEFAULT_T="2" NEXT_SEQ="0" KEY_TAG="1" HIDDEN="F" SORT_DIR="ASC" POS="2" SEQ="1"/><DATA TYPE_CD="S" FIELD_CD="OPEN_DT" FIELD_NM="미결발생일자" FIELD_LEN="10" FIELD_TYPE="DD" DEFAULT_T="3" NEXT_SEQ="0" KEY_TAG="2" HIDDEN="F" SORT_DIR="ASC" POS="3" SEQ="2"/><DATA TYPE_CD="S" FIELD_CD="BP_CD" FIELD_NM="거래처코드" FIELD_LEN="10" FIELD_TYPE="ED" DEFAULT_T="4" NEXT_SEQ="0" KEY_TAG="3" HIDDEN="F" SORT_DIR="ASC" POS="4" SEQ="3"/><DATA TYPE_CD="S" FIELD_CD="BP_NM" FIELD_NM="거래처명" FIELD_LEN="15" FIELD_TYPE="ED" DEFAULT_T="5" NEXT_SEQ="0" KEY_TAG="4" HIDDEN="F" SORT_DIR="ASC" POS="5" SEQ="4"/><DATA TYPE_CD="S" FIELD_CD="MGNT_CD1" FIELD_NM="미결관리1" FIELD_LEN="15" FIELD_TYPE="ED" DEFAULT_T="6" NEXT_SEQ="0" KEY_TAG="5" HIDDEN="T" SORT_DIR="ASC" POS="6" SEQ="5"/><DATA TYPE_CD="S" FIELD_CD="MGNT_VAL1" FIELD_NM="미결항목명1" FIELD_LEN="15" FIELD_TYPE="ED" DEFAULT_T="7" NEXT_SEQ="0" KEY_TAG="6" HIDDEN="T" SORT_DIR="ASC" POS="7" SEQ="6"/><DATA TYPE_CD="S" FIELD_CD="MGNT_CD2" FIELD_NM="미결관리2" FIELD_LEN="15" FIELD_TYPE="ED" DEFAULT_T="8" NEXT_SEQ="0" KEY_TAG="7" HIDDEN="T" SORT_DIR="ASC" POS="8" SEQ="7"/><DATA TYPE_CD="S" FIELD_CD="MGNT_VAL2" FIELD_NM="미결항목명2" FIELD_LEN="15" FIELD_TYPE="ED" DEFAULT_T="9" NEXT_SEQ="0" KEY_TAG="8" HIDDEN="T" SORT_DIR="ASC" POS="9" SEQ="8"/><DATA TYPE_CD="S" FIELD_CD="ACCT_CD" FIELD_NM="계정코드" FIELD_LEN="10" FIELD_TYPE="ED" DEFAULT_T="10" NEXT_SEQ="0" KEY_TAG="9" HIDDEN="F" SORT_DIR="ASC" POS="10" SEQ="9"/><DATA TYPE_CD="S" FIELD_CD="ACCT_NM" FIELD_NM="계정코드명" FIELD_LEN="12" FIELD_TYPE="ED" DEFAULT_T="11" NEXT_SEQ="0" KEY_TAG="10" HIDDEN="F" SORT_DIR="ASC" POS="11" SEQ="10"/><DATA TYPE_CD="S" FIELD_CD="DR_CR_FG" FIELD_NM="차대구분" FIELD_LEN="8" FIELD_TYPE="HH" DEFAULT_T="L" NEXT_SEQ="0" KEY_TAG="11" HIDDEN="S" SORT_DIR="ASC" POS="12" SEQ="11"/><DATA TYPE_CD="S" FIELD_CD="DR_CR_NM" FIELD_NM="차대구분" FIELD_LEN="8" FIELD_TYPE="ED" DEFAULT_T="L" NEXT_SEQ="0" KEY_TAG="12" HIDDEN="F" SORT_DIR="ASC" POS="13" SEQ="12"/><DATA TYPE_CD="S" FIELD_CD="DOC_CUR" FIELD_NM="거래통화" FIELD_LEN="8" FIELD_TYPE="ED" DEFAULT_T="L" NEXT_SEQ="0" KEY_TAG="13" HIDDEN="F" SORT_DIR="ASC" POS="14" SEQ="13"/><DATA TYPE_CD="S" FIELD_CD="BAL_AMT" FIELD_NM="잔액" FIELD_LEN="14" FIELD_TYPE="FA" DEFAULT_T="L" NEXT_SEQ="0" KEY_TAG="14" HIDDEN="F" SORT_DIR="ASC" POS="15" SEQ="14"/><DATA TYPE_CD="S" FIELD_CD="OPEN_AMT" FIELD_NM="발생금액" FIELD_LEN="14" FIELD_TYPE="FA" DEFAULT_T="L" NEXT_SEQ="0" KEY_TAG="15" HIDDEN="F" SORT_DIR="ASC" POS="16" SEQ="15"/><DATA TYPE_CD="S" FIELD_CD="CLS_AMT" FIELD_NM="반제금액" FIELD_LEN="14" FIELD_TYPE="FA" DEFAULT_T="L" NEXT_SEQ="0" KEY_TAG="16" HIDDEN="F" SORT_DIR="ASC" POS="17" SEQ="16"/><DATA TYPE_CD="S" FIELD_CD="OPEN_TYPE_CD" FIELD_NM="미결구분" FIELD_LEN="9" FIELD_TYPE="HH" DEFAULT_T="L" NEXT_SEQ="0" KEY_TAG="17" HIDDEN="S" SORT_DIR="ASC" POS="18" SEQ="17"/><DATA TYPE_CD="S" FIELD_CD="OPEN_TYPE_NM" FIELD_NM="미결구분" FIELD_LEN="9" FIELD_TYPE="ED" DEFAULT_T="L" NEXT_SEQ="0" KEY_TAG="18" HIDDEN="F" SORT_DIR="ASC" POS="19" SEQ="18"/><DATA TYPE_CD="S" FIELD_CD="OPEN_NO" FIELD_NM="미결번호" FIELD_LEN="15" FIELD_TYPE="ED" DEFAULT_T="L" NEXT_SEQ="0" KEY_TAG="19" HIDDEN="F" SORT_DIR="ASC" POS="20" SEQ="19"/><DATA TYPE_CD="S" FIELD_CD="DUE_DT" FIELD_NM="만기일" FIELD_LEN="10" FIELD_TYPE="ED" DEFAULT_T="1" NEXT_SEQ="0" KEY_TAG="20" HIDDEN="F" SORT_DIR="ASC" POS="1" SEQ="20"/><DATA TYPE_CD="S" FIELD_CD="ORG_CHANGE_ID" FIELD_NM="조직변경아이디" FIELD_LEN="14" FIELD_TYPE="ED" DEFAULT_T="L" NEXT_SEQ="0" KEY_TAG="21" HIDDEN="F" SORT_DIR="ASC" POS="21" SEQ="21"/><DATA TYPE_CD="S" FIELD_CD="DEPT_CD" FIELD_NM="부서코드" FIELD_LEN="10" FIELD_TYPE="ED" DEFAULT_T="L" NEXT_SEQ="0" KEY_TAG="22" HIDDEN="F" SORT_DIR="ASC" POS="22" SEQ="22"/><DATA TYPE_CD="S" FIELD_CD="DEPT_NM" FIELD_NM="부서명" FIELD_LEN="14" FIELD_TYPE="ED" DEFAULT_T="L" NEXT_SEQ="0" KEY_TAG="23" HIDDEN="F" SORT_DIR="ASC" POS="23" SEQ="23"/><DATA TYPE_CD="S" FIELD_CD="BIZ_AREA_CD" FIELD_NM="사업장코드" FIELD_LEN="10" FIELD_TYPE="ED" DEFAULT_T="L" NEXT_SEQ="0" KEY_TAG="24" HIDDEN="T" SORT_DIR="ASC" POS="24" SEQ="24"/><DATA TYPE_CD="S" FIELD_CD="BIZ_AREA_NM" FIELD_NM="사업장명" FIELD_LEN="14" FIELD_TYPE="ED" DEFAULT_T="L" NEXT_SEQ="0" KEY_TAG="25" HIDDEN="F" SORT_DIR="ASC" POS="25" SEQ="25"/><DATA TYPE_CD="S" FIELD_CD="BAL_AMT" FIELD_NM="반제할금액" FIELD_LEN="14" FIELD_TYPE="FA" DEFAULT_T="L" NEXT_SEQ="0" KEY_TAG="26" HIDDEN="F" SORT_DIR="ASC" POS="26" SEQ="26"/><DATA TYPE_CD="S" FIELD_CD="GL_SEQ" FIELD_NM="미결순번" FIELD_LEN="14" FIELD_TYPE="HH" DEFAULT_T="L" NEXT_SEQ="0" KEY_TAG="27" HIDDEN="S" SORT_DIR="ASC" POS="27" SEQ="27"/><DATA TYPE_CD="S" FIELD_CD="XCH_RATE" FIELD_NM="환율" FIELD_LEN="10" FIELD_TYPE="F5" DEFAULT_T="L" NEXT_SEQ="0" KEY_TAG="28" HIDDEN="F" SORT_DIR="ASC" POS="28" SEQ="28"/><DATA TYPE_CD="S" FIELD_CD="GL_DESC" FIELD_NM="적  요 " FIELD_LEN="30" FIELD_TYPE="ED" DEFAULT_T="L" NEXT_SEQ="0" KEY_TAG="29" HIDDEN="F" SORT_DIR="ASC" POS="29" SEQ="29"/></vspdData></Root>
